{
   "created_at": "Mon Mar 07 20:16:07 +0000 2022",
   "id": 1500928299513569284,
   "id_str": "1500928299513569284",
   "text": "In order to implement this decision, we\u2019re going to have to provide additional resources and hold DoD\u2019s feet to the\u2026 https://t.co/CLFENcVvm4",
   "source": "<a href=\"http://twitter.com/download/iphone\" rel=\"nofollow\">Twitter for iPhone</a>",
   "truncated": true,
   "in_reply_to_status_id": 1500928298276339724,
   "in_reply_to_status_id_str": "1500928298276339724",
   "in_reply_to_user_id": 1262099252,
   "in_reply_to_user_id_str": "1262099252",
   "in_reply_to_screen_name": "SenBrianSchatz",
   "user": {
      "id": 1262099252,
      "id_str": "1262099252",
      "name": "Senator Brian Schatz",
      "screen_name": "SenBrianSchatz",
      "location": null,
      "url": "http://www.schatz.senate.gov/",
      "description": "Tweets from the Office of U.S. Senator Brian Schatz, representing the great state of Hawaii.",
      "translator_type": "none",
      "protected": false,
      "verified": true,
      "followers_count": 51008,
      "friends_count": 1305,
      "listed_count": 1275,
      "favourites_count": 119,
      "statuses_count": 2234,
      "created_at": "Tue Mar 12 14:23:20 +0000 2013",
      "utc_offset": null,
      "time_zone": null,
      "geo_enabled": true,
      "lang": null,
      "contributors_enabled": false,
      "is_translator": false,
      "profile_background_color": "C0DEED",
      "profile_background_image_url": "http://abs.twimg.com/images/themes/theme1/bg.png",
      "profile_background_image_url_https": "https://abs.twimg.com/images/themes/theme1/bg.png",
      "profile_background_tile": false,
      "profile_link_color": "106B98",
      "profile_sidebar_border_color": "FFFFFF",
      "profile_sidebar_fill_color": "DDEEF6",
      "profile_text_color": "333333",
      "profile_use_background_image": true,
      "profile_image_url": "http://pbs.twimg.com/profile_images/849770568677298176/dzXWNsOx_normal.jpg",
      "profile_image_url_https": "https://pbs.twimg.com/profile_images/849770568677298176/dzXWNsOx_normal.jpg",
      "profile_banner_url": "https://pbs.twimg.com/profile_banners/1262099252/1433862030",
      "default_profile": false,
      "default_profile_image": false,
      "following": null,
      "follow_request_sent": null,
      "notifications": null,
      "withheld_in_countries": []
   },
   "geo": null,
   "coordinates": null,
   "place": null,
   "contributors": null,
   "is_quote_status": false,
   "extended_tweet": {
      "full_text": "In order to implement this decision, we\u2019re going to have to provide additional resources and hold DoD\u2019s feet to the fire through congressional oversight. I will continue to work with our federal and state partners to see this through.",
      "display_text_range": [
         0,
         234
      ],
      "entities": {
         "hashtags": [],
         "urls": [],
         "user_mentions": [],
         "symbols": []
      }
   },
   "quote_count": 0,
   "reply_count": 0,
   "retweet_count": 0,
   "favorite_count": 0,
   "entities": {
      "hashtags": [],
      "urls": [
         {
            "url": "https://t.co/CLFENcVvm4",
            "expanded_url": "https://twitter.com/i/web/status/1500928299513569284",
            "display_url": "twitter.com/i/web/status/1\u2026",
            "indices": [
               117,
               140
            ]
         }
      ],
      "user_mentions": [],
      "symbols": []
   },
   "favorited": false,
   "retweeted": false,
   "filter_level": "low",
   "lang": "en",
   "timestamp_ms": "1646684167160"
}