{
   "created_at": "Mon Mar 07 23:11:58 +0000 2022",
   "id": 1500972555619942400,
   "id_str": "1500972555619942400",
   "text": "RT @RepMTG: You\u2019re not going to believe what\u2019s inside the Democrats\u2019 $1.5 TRILLION Omnibus Bill. Let me tell you\u2026 https://t.co/dYoYSWuYrE",
   "source": "<a href=\"https://mobile.twitter.com\" rel=\"nofollow\">Twitter Web App</a>",
   "truncated": false,
   "in_reply_to_status_id": null,
   "in_reply_to_status_id_str": null,
   "in_reply_to_user_id": null,
   "in_reply_to_user_id_str": null,
   "in_reply_to_screen_name": null,
   "user": {
      "id": 3320699257,
      "id_str": "3320699257",
      "name": "Casper Stockham - fighting for the Republic!",
      "screen_name": "Casper4Colorado",
      "location": "Colorado, USA",
      "url": "http://casperforcolorado.com",
      "description": "AFR Founder, former US Congressional Candidate CO, Christian Conservative, VET. Saving the Republic one snowflake at a time! #LGB",
      "translator_type": "none",
      "protected": false,
      "verified": true,
      "followers_count": 3860,
      "friends_count": 629,
      "listed_count": 35,
      "favourites_count": 9449,
      "statuses_count": 7984,
      "created_at": "Wed Aug 19 22:27:26 +0000 2015",
      "utc_offset": null,
      "time_zone": null,
      "geo_enabled": false,
      "lang": null,
      "contributors_enabled": false,
      "is_translator": false,
      "profile_background_color": "C0DEED",
      "profile_background_image_url": "http://abs.twimg.com/images/themes/theme1/bg.png",
      "profile_background_image_url_https": "https://abs.twimg.com/images/themes/theme1/bg.png",
      "profile_background_tile": false,
      "profile_link_color": "0084B4",
      "profile_sidebar_border_color": "000000",
      "profile_sidebar_fill_color": "000000",
      "profile_text_color": "000000",
      "profile_use_background_image": true,
      "profile_image_url": "http://pbs.twimg.com/profile_images/1348010389330558976/GfLf3Ybl_normal.jpg",
      "profile_image_url_https": "https://pbs.twimg.com/profile_images/1348010389330558976/GfLf3Ybl_normal.jpg",
      "profile_banner_url": "https://pbs.twimg.com/profile_banners/3320699257/1639064021",
      "default_profile": false,
      "default_profile_image": false,
      "following": null,
      "follow_request_sent": null,
      "notifications": null,
      "withheld_in_countries": []
   },
   "geo": null,
   "coordinates": null,
   "place": null,
   "contributors": null,
   "retweeted_status": {
      "created_at": "Mon Mar 07 22:30:29 +0000 2022",
      "id": 1500962114399350797,
      "id_str": "1500962114399350797",
      "text": "You\u2019re not going to believe what\u2019s inside the Democrats\u2019 $1.5 TRILLION Omnibus Bill. Let me tell you\u2026 https://t.co/dYoYSWuYrE",
      "source": "<a href=\"http://twitter.com/download/iphone\" rel=\"nofollow\">Twitter for iPhone</a>",
      "truncated": false,
      "in_reply_to_status_id": null,
      "in_reply_to_status_id_str": null,
      "in_reply_to_user_id": null,
      "in_reply_to_user_id_str": null,
      "in_reply_to_screen_name": null,
      "user": {
         "id": 1344356576786866176,
         "id_str": "1344356576786866176",
         "name": "Rep. Marjorie Taylor Greene",
         "screen_name": "RepMTG",
         "location": "Rome, GA",
         "url": "http://greene.house.gov",
         "description": "Wife, Mother, and Congresswoman representing Georgia\u2019s 14th District",
         "translator_type": "none",
         "protected": false,
         "verified": true,
         "followers_count": 453692,
         "friends_count": 92,
         "listed_count": 1594,
         "favourites_count": 77,
         "statuses_count": 712,
         "created_at": "Wed Dec 30 18:57:01 +0000 2020",
         "utc_offset": null,
         "time_zone": null,
         "geo_enabled": true,
         "lang": null,
         "contributors_enabled": false,
         "is_translator": false,
         "profile_background_color": "F5F8FA",
         "profile_background_image_url": "",
         "profile_background_image_url_https": "",
         "profile_background_tile": false,
         "profile_link_color": "1DA1F2",
         "profile_sidebar_border_color": "C0DEED",
         "profile_sidebar_fill_color": "DDEEF6",
         "profile_text_color": "333333",
         "profile_use_background_image": true,
         "profile_image_url": "http://pbs.twimg.com/profile_images/1344356993017008128/vrBGKcjd_normal.jpg",
         "profile_image_url_https": "https://pbs.twimg.com/profile_images/1344356993017008128/vrBGKcjd_normal.jpg",
         "profile_banner_url": "https://pbs.twimg.com/profile_banners/1344356576786866176/1609628400",
         "default_profile": true,
         "default_profile_image": false,
         "following": null,
         "follow_request_sent": null,
         "notifications": null,
         "withheld_in_countries": []
      },
      "geo": null,
      "coordinates": null,
      "place": null,
      "contributors": null,
      "is_quote_status": false,
      "quote_count": 35,
      "reply_count": 400,
      "retweet_count": 442,
      "favorite_count": 953,
      "entities": {
         "hashtags": [],
         "urls": [
            {
               "url": "https://t.co/dYoYSWuYrE",
               "expanded_url": "https://twitter.com/i/broadcasts/1yNxaYdpLnExj",
               "display_url": "twitter.com/i/broadcasts/1\u2026",
               "indices": [
                  102,
                  125
               ]
            }
         ],
         "user_mentions": [],
         "symbols": []
      },
      "favorited": false,
      "retweeted": false,
      "possibly_sensitive": false,
      "filter_level": "low",
      "lang": "en"
   },
   "is_quote_status": false,
   "quote_count": 0,
   "reply_count": 0,
   "retweet_count": 0,
   "favorite_count": 0,
   "entities": {
      "hashtags": [],
      "urls": [
         {
            "url": "https://t.co/dYoYSWuYrE",
            "expanded_url": "https://twitter.com/i/broadcasts/1yNxaYdpLnExj",
            "display_url": "twitter.com/i/broadcasts/1\u2026",
            "indices": [
               114,
               137
            ]
         }
      ],
      "user_mentions": [
         {
            "screen_name": "RepMTG",
            "name": "Rep. Marjorie Taylor Greene",
            "id": 1344356576786866176,
            "id_str": "1344356576786866176",
            "indices": [
               3,
               10
            ]
         }
      ],
      "symbols": []
   },
   "favorited": false,
   "retweeted": false,
   "possibly_sensitive": false,
   "filter_level": "low",
   "lang": "en",
   "timestamp_ms": "1646694718638"
}